Metadata-Version: 2.1
Name: bodystuff
Version: 0.0.6
Summary: Utilities for my tools
Author: Body Alhoha
Author-email: bodyalhoha@gmail.com
Classifier: Programming Language :: Python :: 3
Classifier: License :: OSI Approved :: MIT License
Classifier: Operating System :: OS Independent
Requires-Python: >=3.6
License-File: LICENSE
